{
  "parameters": {
    "RepetitionCount": 3,
    "CleanBuild": false,
    "StepCount": 20,
    "Reference": true,
    "Common": true,
    "Dedicated": false,
    "JVM": true,
    "JS": true,
    "Native": true,
    "FlushEarly": [
      false
    ],
    "InstrumentPropertyAccessors": [
      false
    ],
    "TestKIR": [
      false
    ]
  },
  "machineInfo": {
    "DeviceManufacturer": "Microsoft Corporation",
    "DeviceModel": "Virtual Machine",
    "OS": "Ubuntu 24.04.4 LTS",
    "OSArchitecture": "x86_64",
    "CPU": "AMD EPYC 7763 64-Core Processor",
    "CPUCores": 2,
    "CPULogicalProcessors": 4,
    "TotalRAMGB": 15.61,
    "AvailableRAMGB": 13.64,
    "DiskSizeGB": 145,
    "SystemDriveFreeSpaceGB": 86,
    "SystemUptimeHours": 0.05,
    "TimeZone": "Etc/UTC",
    "Username": "runner",
    "RunningProcessCount": 159,
    "IsVirtualMachine": true,
    "PowerShellVersion": "7.4.14",
    "JavaVersion": "21.0.10",
    "JavaDistribution": "\"21.0.10\"",
    "NodeVersion": "v22.22.2",
    "PythonVersion": "Python 3.12.3",
    "GradleVersion": "System.Object[]",
    "KotlinVersion": "Kotlin:        2.2.0",
    "GitCommitHash": "13aa2557a67f8621d0381b187f3917bd2f874964",
    "GitBranch": "main",
    "CollectionTimestamp": "2026-04-09 01:10:32"
  },
  "buildTimeMs": 6095.1203,
  "executable": "CommonMain-plain-node",
  "repetitions": 3,
  "times": [
    197802.0,
    181904.0,
    151509.0
  ],
  "statistics": {
    "count": 3,
    "mean": 177071.66666666666,
    "median": 197802.0,
    "stddev": 23521.778128647784,
    "min": 151509.0,
    "max": 197802.0,
    "ci95": {
      "lower": 118676.35544877482,
      "upper": 235466.9778845585
    }
  }
}
