[
  {
    "mean": 62709.0,
    "median": 81821.0,
    "stddev": 16807.94553180132,
    "min": 50228.0,
    "max": 81821.0,
    "ci95_lower": 20981.490927566745,
    "ci95_upper": 104436.50907243325,
    "executable": "commonmain-plain-jar",
    "buildTimeMs": 1932.2786,
    "RepetitionCount": 3,
    "CleanBuild": false,
    "StepCount": 20,
    "JS": true,
    "Dedicated": false,
    "InstrumentPropertyAccessors": [
      false
    ],
    "JVM": true,
    "TestKIR": [
      false
    ],
    "WarmupCount": 0,
    "CILabel": "ci-linux-small",
    "Reference": true,
    "FlushEarly": [
      false
    ],
    "Common": true,
    "Native": true,
    "CollectionTimestamp": "2026-04-10 19:11:15",
    "GitCommitHash": "ef0733869127e2d0f101f439d285364ac76ff0d8",
    "GitBranch": "main",
    "DeviceManufacturer": "Microsoft Corporation",
    "DeviceModel": "Virtual Machine",
    "IsVirtualMachine": true,
    "OS": "Ubuntu 24.04.4 LTS",
    "OSArchitecture": "x86_64",
    "TimeZone": "Etc/UTC",
    "Username": "runner",
    "CPU": "AMD EPYC 7763 64-Core Processor",
    "CPUCores": 2,
    "CPULogicalProcessors": 4,
    "TotalRAMGB": 15.62,
    "AvailableRAMGB": 13.95,
    "DiskSizeGB": 145,
    "SystemDriveFreeSpaceGB": 86,
    "SystemUptimeHours": 0.02,
    "RunningProcessCount": 158,
    "PowerShellVersion": "7.4.14",
    "JavaVersion": "21.0.10",
    "JavaDistribution": "\"21.0.10\"",
    "NodeVersion": "v22.22.2",
    "PythonVersion": "Python 3.12.3",
    "GradleVersion": "System.Object[]",
    "KotlinVersion": "Kotlin:        2.2.0"
  },
  {
    "mean": null,
    "median": null,
    "stddev": null,
    "min": null,
    "max": null,
    "ci95_lower": null,
    "ci95_upper": null,
    "executable": "commonmain-plain-node",
    "buildTimeMs": 6185.0962,
    "RepetitionCount": 3,
    "CleanBuild": false,
    "StepCount": 20,
    "JS": true,
    "Dedicated": false,
    "InstrumentPropertyAccessors": [
      false
    ],
    "JVM": true,
    "TestKIR": [
      false
    ],
    "WarmupCount": 0,
    "CILabel": "ci-linux-small",
    "Reference": true,
    "FlushEarly": [
      false
    ],
    "Common": true,
    "Native": true,
    "CollectionTimestamp": "2026-04-10 19:11:15",
    "GitCommitHash": "ef0733869127e2d0f101f439d285364ac76ff0d8",
    "GitBranch": "main",
    "DeviceManufacturer": "Microsoft Corporation",
    "DeviceModel": "Virtual Machine",
    "IsVirtualMachine": true,
    "OS": "Ubuntu 24.04.4 LTS",
    "OSArchitecture": "x86_64",
    "TimeZone": "Etc/UTC",
    "Username": "runner",
    "CPU": "AMD EPYC 7763 64-Core Processor",
    "CPUCores": 2,
    "CPULogicalProcessors": 4,
    "TotalRAMGB": 15.62,
    "AvailableRAMGB": 13.95,
    "DiskSizeGB": 145,
    "SystemDriveFreeSpaceGB": 86,
    "SystemUptimeHours": 0.02,
    "RunningProcessCount": 158,
    "PowerShellVersion": "7.4.14",
    "JavaVersion": "21.0.10",
    "JavaDistribution": "\"21.0.10\"",
    "NodeVersion": "v22.22.2",
    "PythonVersion": "Python 3.12.3",
    "GradleVersion": "System.Object[]",
    "KotlinVersion": "Kotlin:        2.2.0"
  },
  {
    "mean": 9348.0,
    "median": 10285.0,
    "stddev": 871.7333307841337,
    "min": 8561.0,
    "max": 10285.0,
    "ci95_lower": 7183.829465283909,
    "ci95_upper": 11512.170534716091,
    "executable": "commonmain-plain-exe",
    "buildTimeMs": 2407.3643,
    "RepetitionCount": 3,
    "CleanBuild": false,
    "StepCount": 20,
    "JS": true,
    "Dedicated": false,
    "InstrumentPropertyAccessors": [
      false
    ],
    "JVM": true,
    "TestKIR": [
      false
    ],
    "WarmupCount": 0,
    "CILabel": "ci-linux-small",
    "Reference": true,
    "FlushEarly": [
      false
    ],
    "Common": true,
    "Native": true,
    "CollectionTimestamp": "2026-04-10 19:11:15",
    "GitCommitHash": "ef0733869127e2d0f101f439d285364ac76ff0d8",
    "GitBranch": "main",
    "DeviceManufacturer": "Microsoft Corporation",
    "DeviceModel": "Virtual Machine",
    "IsVirtualMachine": true,
    "OS": "Ubuntu 24.04.4 LTS",
    "OSArchitecture": "x86_64",
    "TimeZone": "Etc/UTC",
    "Username": "runner",
    "CPU": "AMD EPYC 7763 64-Core Processor",
    "CPUCores": 2,
    "CPULogicalProcessors": 4,
    "TotalRAMGB": 15.62,
    "AvailableRAMGB": 13.95,
    "DiskSizeGB": 145,
    "SystemDriveFreeSpaceGB": 86,
    "SystemUptimeHours": 0.02,
    "RunningProcessCount": 158,
    "PowerShellVersion": "7.4.14",
    "JavaVersion": "21.0.10",
    "JavaDistribution": "\"21.0.10\"",
    "NodeVersion": "v22.22.2",
    "PythonVersion": "Python 3.12.3",
    "GradleVersion": "System.Object[]",
    "KotlinVersion": "Kotlin:        2.2.0"
  },
  {
    "mean": 139293.0,
    "median": 177644.0,
    "stddev": 34994.52747216341,
    "min": 109094.0,
    "max": 177644.0,
    "ci95_lower": 52415.37061826562,
    "ci95_upper": 226170.62938173438,
    "executable": "commonmain-k-perf-flushEarly-false-propAccessors-false-testKIR-false-jar",
    "buildTimeMs": 2042.8278,
    "RepetitionCount": 3,
    "CleanBuild": false,
    "StepCount": 20,
    "JS": true,
    "Dedicated": false,
    "InstrumentPropertyAccessors": [
      false
    ],
    "JVM": true,
    "TestKIR": [
      false
    ],
    "WarmupCount": 0,
    "CILabel": "ci-linux-small",
    "Reference": true,
    "FlushEarly": [
      false
    ],
    "Common": true,
    "Native": true,
    "CollectionTimestamp": "2026-04-10 19:11:15",
    "GitCommitHash": "ef0733869127e2d0f101f439d285364ac76ff0d8",
    "GitBranch": "main",
    "DeviceManufacturer": "Microsoft Corporation",
    "DeviceModel": "Virtual Machine",
    "IsVirtualMachine": true,
    "OS": "Ubuntu 24.04.4 LTS",
    "OSArchitecture": "x86_64",
    "TimeZone": "Etc/UTC",
    "Username": "runner",
    "CPU": "AMD EPYC 7763 64-Core Processor",
    "CPUCores": 2,
    "CPULogicalProcessors": 4,
    "TotalRAMGB": 15.62,
    "AvailableRAMGB": 13.95,
    "DiskSizeGB": 145,
    "SystemDriveFreeSpaceGB": 86,
    "SystemUptimeHours": 0.02,
    "RunningProcessCount": 158,
    "PowerShellVersion": "7.4.14",
    "JavaVersion": "21.0.10",
    "JavaDistribution": "\"21.0.10\"",
    "NodeVersion": "v22.22.2",
    "PythonVersion": "Python 3.12.3",
    "GradleVersion": "System.Object[]",
    "KotlinVersion": "Kotlin:        2.2.0"
  },
  {
    "mean": null,
    "median": null,
    "stddev": null,
    "min": null,
    "max": null,
    "ci95_lower": null,
    "ci95_upper": null,
    "executable": "commonmain-k-perf-flushEarly-false-propAccessors-false-testKIR-false-node",
    "buildTimeMs": 4219.9772,
    "RepetitionCount": 3,
    "CleanBuild": false,
    "StepCount": 20,
    "JS": true,
    "Dedicated": false,
    "InstrumentPropertyAccessors": [
      false
    ],
    "JVM": true,
    "TestKIR": [
      false
    ],
    "WarmupCount": 0,
    "CILabel": "ci-linux-small",
    "Reference": true,
    "FlushEarly": [
      false
    ],
    "Common": true,
    "Native": true,
    "CollectionTimestamp": "2026-04-10 19:11:15",
    "GitCommitHash": "ef0733869127e2d0f101f439d285364ac76ff0d8",
    "GitBranch": "main",
    "DeviceManufacturer": "Microsoft Corporation",
    "DeviceModel": "Virtual Machine",
    "IsVirtualMachine": true,
    "OS": "Ubuntu 24.04.4 LTS",
    "OSArchitecture": "x86_64",
    "TimeZone": "Etc/UTC",
    "Username": "runner",
    "CPU": "AMD EPYC 7763 64-Core Processor",
    "CPUCores": 2,
    "CPULogicalProcessors": 4,
    "TotalRAMGB": 15.62,
    "AvailableRAMGB": 13.95,
    "DiskSizeGB": 145,
    "SystemDriveFreeSpaceGB": 86,
    "SystemUptimeHours": 0.02,
    "RunningProcessCount": 158,
    "PowerShellVersion": "7.4.14",
    "JavaVersion": "21.0.10",
    "JavaDistribution": "\"21.0.10\"",
    "NodeVersion": "v22.22.2",
    "PythonVersion": "Python 3.12.3",
    "GradleVersion": "System.Object[]",
    "KotlinVersion": "Kotlin:        2.2.0"
  },
  {
    "mean": 51825.0,
    "median": 54441.0,
    "stddev": 2579.796115975059,
    "min": 49283.0,
    "max": 54441.0,
    "ci95_lower": 45420.38227734603,
    "ci95_upper": 58229.61772265397,
    "executable": "commonmain-k-perf-flushEarly-false-propAccessors-false-testKIR-false-exe",
    "buildTimeMs": 2751.587,
    "RepetitionCount": 3,
    "CleanBuild": false,
    "StepCount": 20,
    "JS": true,
    "Dedicated": false,
    "InstrumentPropertyAccessors": [
      false
    ],
    "JVM": true,
    "TestKIR": [
      false
    ],
    "WarmupCount": 0,
    "CILabel": "ci-linux-small",
    "Reference": true,
    "FlushEarly": [
      false
    ],
    "Common": true,
    "Native": true,
    "CollectionTimestamp": "2026-04-10 19:11:15",
    "GitCommitHash": "ef0733869127e2d0f101f439d285364ac76ff0d8",
    "GitBranch": "main",
    "DeviceManufacturer": "Microsoft Corporation",
    "DeviceModel": "Virtual Machine",
    "IsVirtualMachine": true,
    "OS": "Ubuntu 24.04.4 LTS",
    "OSArchitecture": "x86_64",
    "TimeZone": "Etc/UTC",
    "Username": "runner",
    "CPU": "AMD EPYC 7763 64-Core Processor",
    "CPUCores": 2,
    "CPULogicalProcessors": 4,
    "TotalRAMGB": 15.62,
    "AvailableRAMGB": 13.95,
    "DiskSizeGB": 145,
    "SystemDriveFreeSpaceGB": 86,
    "SystemUptimeHours": 0.02,
    "RunningProcessCount": 158,
    "PowerShellVersion": "7.4.14",
    "JavaVersion": "21.0.10",
    "JavaDistribution": "\"21.0.10\"",
    "NodeVersion": "v22.22.2",
    "PythonVersion": "Python 3.12.3",
    "GradleVersion": "System.Object[]",
    "KotlinVersion": "Kotlin:        2.2.0"
  }
]
