[
  {
    "mean": 62199.666666666664,
    "median": 68354.0,
    "stddev": 6262.149817221984,
    "min": 55835.0,
    "max": 68354.0,
    "ci95_lower": 46653.214971147485,
    "ci95_upper": 77746.11836218584,
    "executable": "commonmain-plain-jar",
    "buildTimeMs": 2960.1261,
    "RepetitionCount": 3,
    "CleanBuild": false,
    "StepCount": 20,
    "Native": true,
    "Enabled": [
      true
    ],
    "Methods": [
      ".*"
    ],
    "InstrumentPropertyAccessors": [
      false
    ],
    "CILabel": "ci-windows-small",
    "Dedicated": false,
    "JVM": true,
    "JS": true,
    "FlushEarly": [
      false
    ],
    "TestKIR": [
      false
    ],
    "Common": true,
    "Reference": true,
    "CollectionTimestamp": "2026-06-19 04:08:49",
    "GitCommitHash": "be04b4c7ef586e83a5426f6ec6e5baca67cd70f9",
    "GitBranch": "main",
    "DeviceManufacturer": "Microsoft Corporation",
    "DeviceModel": "Virtual Machine",
    "IsVirtualMachine": true,
    "OS": "Microsoft Windows Server 2025 Datacenter 10.0.26100",
    "OSArchitecture": "64-bit",
    "WindowsBuildNumber": "26100",
    "TimeZone": "UTC",
    "Username": "runneradmin",
    "BIOSVersion": "Hyper-V UEFI Release v4.1",
    "BIOSManufacturer": "Microsoft Corporation",
    "SecureBootEnabled": false,
    "HyperVEnabled": true,
    "CPU": "AMD EPYC 9V74 80-Core Processor",
    "CPUCores": 2,
    "CPULogicalProcessors": 4,
    "CPUMaxClockSpeedMHz": 2596,
    "TotalRAMGB": 15.99,
    "AvailableRAMGB": 12.1,
    "RAMModuleCount": 2,
    "RAMManufacturer": "Microsoft Corporation",
    "RAMPartNumber": "None",
    "RAMModuleCapacitiesGB": "1 + 15",
    "DiskModel": "Microsoft Virtual Disk",
    "DiskSizeGB": 150.0,
    "DiskMediaType": "Fixed hard disk media",
    "DiskInterfaceType": "SCSI",
    "SystemDriveFreeSpaceGB": 30.9,
    "PowerPlan": "High performance",
    "SystemUptimeHours": 0.6,
    "RunningProcessCount": 128,
    "WindowsDefenderEnabled": true,
    "WindowsDefenderRealTimeProtection": false,
    "PowerShellVersion": "7.6.2",
    "JavaVersion": "21.0.11",
    "JavaDistribution": "\"21.0.11\"",
    "NodeVersion": "v22.22.3",
    "PythonVersion": "Python 3.12.10",
    "GradleVersion": "System.Object[]",
    "KotlinVersion": "Kotlin:        2.2.0"
  },
  {
    "mean": null,
    "median": null,
    "stddev": null,
    "min": null,
    "max": null,
    "ci95_lower": null,
    "ci95_upper": null,
    "executable": "commonmain-plain-node",
    "buildTimeMs": 7286.1594,
    "RepetitionCount": 3,
    "CleanBuild": false,
    "StepCount": 20,
    "Native": true,
    "Enabled": [
      true
    ],
    "Methods": [
      ".*"
    ],
    "InstrumentPropertyAccessors": [
      false
    ],
    "CILabel": "ci-windows-small",
    "Dedicated": false,
    "JVM": true,
    "JS": true,
    "FlushEarly": [
      false
    ],
    "TestKIR": [
      false
    ],
    "Common": true,
    "Reference": true,
    "CollectionTimestamp": "2026-06-19 04:08:49",
    "GitCommitHash": "be04b4c7ef586e83a5426f6ec6e5baca67cd70f9",
    "GitBranch": "main",
    "DeviceManufacturer": "Microsoft Corporation",
    "DeviceModel": "Virtual Machine",
    "IsVirtualMachine": true,
    "OS": "Microsoft Windows Server 2025 Datacenter 10.0.26100",
    "OSArchitecture": "64-bit",
    "WindowsBuildNumber": "26100",
    "TimeZone": "UTC",
    "Username": "runneradmin",
    "BIOSVersion": "Hyper-V UEFI Release v4.1",
    "BIOSManufacturer": "Microsoft Corporation",
    "SecureBootEnabled": false,
    "HyperVEnabled": true,
    "CPU": "AMD EPYC 9V74 80-Core Processor",
    "CPUCores": 2,
    "CPULogicalProcessors": 4,
    "CPUMaxClockSpeedMHz": 2596,
    "TotalRAMGB": 15.99,
    "AvailableRAMGB": 12.1,
    "RAMModuleCount": 2,
    "RAMManufacturer": "Microsoft Corporation",
    "RAMPartNumber": "None",
    "RAMModuleCapacitiesGB": "1 + 15",
    "DiskModel": "Microsoft Virtual Disk",
    "DiskSizeGB": 150.0,
    "DiskMediaType": "Fixed hard disk media",
    "DiskInterfaceType": "SCSI",
    "SystemDriveFreeSpaceGB": 30.9,
    "PowerPlan": "High performance",
    "SystemUptimeHours": 0.6,
    "RunningProcessCount": 128,
    "WindowsDefenderEnabled": true,
    "WindowsDefenderRealTimeProtection": false,
    "PowerShellVersion": "7.6.2",
    "JavaVersion": "21.0.11",
    "JavaDistribution": "\"21.0.11\"",
    "NodeVersion": "v22.22.3",
    "PythonVersion": "Python 3.12.10",
    "GradleVersion": "System.Object[]",
    "KotlinVersion": "Kotlin:        2.2.0"
  },
  {
    "mean": 12527.333333333334,
    "median": 12621.0,
    "stddev": 90.66605391949807,
    "min": 12440.0,
    "max": 12621.0,
    "ci95_lower": 12302.245229595166,
    "ci95_upper": 12752.421437071502,
    "executable": "commonmain-plain-win-exe",
    "buildTimeMs": 104633.6811,
    "RepetitionCount": 3,
    "CleanBuild": false,
    "StepCount": 20,
    "Native": true,
    "Enabled": [
      true
    ],
    "Methods": [
      ".*"
    ],
    "InstrumentPropertyAccessors": [
      false
    ],
    "CILabel": "ci-windows-small",
    "Dedicated": false,
    "JVM": true,
    "JS": true,
    "FlushEarly": [
      false
    ],
    "TestKIR": [
      false
    ],
    "Common": true,
    "Reference": true,
    "CollectionTimestamp": "2026-06-19 04:08:49",
    "GitCommitHash": "be04b4c7ef586e83a5426f6ec6e5baca67cd70f9",
    "GitBranch": "main",
    "DeviceManufacturer": "Microsoft Corporation",
    "DeviceModel": "Virtual Machine",
    "IsVirtualMachine": true,
    "OS": "Microsoft Windows Server 2025 Datacenter 10.0.26100",
    "OSArchitecture": "64-bit",
    "WindowsBuildNumber": "26100",
    "TimeZone": "UTC",
    "Username": "runneradmin",
    "BIOSVersion": "Hyper-V UEFI Release v4.1",
    "BIOSManufacturer": "Microsoft Corporation",
    "SecureBootEnabled": false,
    "HyperVEnabled": true,
    "CPU": "AMD EPYC 9V74 80-Core Processor",
    "CPUCores": 2,
    "CPULogicalProcessors": 4,
    "CPUMaxClockSpeedMHz": 2596,
    "TotalRAMGB": 15.99,
    "AvailableRAMGB": 12.1,
    "RAMModuleCount": 2,
    "RAMManufacturer": "Microsoft Corporation",
    "RAMPartNumber": "None",
    "RAMModuleCapacitiesGB": "1 + 15",
    "DiskModel": "Microsoft Virtual Disk",
    "DiskSizeGB": 150.0,
    "DiskMediaType": "Fixed hard disk media",
    "DiskInterfaceType": "SCSI",
    "SystemDriveFreeSpaceGB": 30.9,
    "PowerPlan": "High performance",
    "SystemUptimeHours": 0.6,
    "RunningProcessCount": 128,
    "WindowsDefenderEnabled": true,
    "WindowsDefenderRealTimeProtection": false,
    "PowerShellVersion": "7.6.2",
    "JavaVersion": "21.0.11",
    "JavaDistribution": "\"21.0.11\"",
    "NodeVersion": "v22.22.3",
    "PythonVersion": "Python 3.12.10",
    "GradleVersion": "System.Object[]",
    "KotlinVersion": "Kotlin:        2.2.0"
  },
  {
    "mean": 126117.33333333333,
    "median": 129779.0,
    "stddev": 5462.243891784157,
    "min": 119839.0,
    "max": 129779.0,
    "ci95_lower": 112556.73301373914,
    "ci95_upper": 139677.93365292752,
    "executable": "commonmain-k-perf-enabled-true-flushEarly-false-propAccessors-false-testKIR-false-jar",
    "buildTimeMs": 3113.483,
    "RepetitionCount": 3,
    "CleanBuild": false,
    "StepCount": 20,
    "Native": true,
    "Enabled": [
      true
    ],
    "Methods": [
      ".*"
    ],
    "InstrumentPropertyAccessors": [
      false
    ],
    "CILabel": "ci-windows-small",
    "Dedicated": false,
    "JVM": true,
    "JS": true,
    "FlushEarly": [
      false
    ],
    "TestKIR": [
      false
    ],
    "Common": true,
    "Reference": true,
    "CollectionTimestamp": "2026-06-19 04:08:49",
    "GitCommitHash": "be04b4c7ef586e83a5426f6ec6e5baca67cd70f9",
    "GitBranch": "main",
    "DeviceManufacturer": "Microsoft Corporation",
    "DeviceModel": "Virtual Machine",
    "IsVirtualMachine": true,
    "OS": "Microsoft Windows Server 2025 Datacenter 10.0.26100",
    "OSArchitecture": "64-bit",
    "WindowsBuildNumber": "26100",
    "TimeZone": "UTC",
    "Username": "runneradmin",
    "BIOSVersion": "Hyper-V UEFI Release v4.1",
    "BIOSManufacturer": "Microsoft Corporation",
    "SecureBootEnabled": false,
    "HyperVEnabled": true,
    "CPU": "AMD EPYC 9V74 80-Core Processor",
    "CPUCores": 2,
    "CPULogicalProcessors": 4,
    "CPUMaxClockSpeedMHz": 2596,
    "TotalRAMGB": 15.99,
    "AvailableRAMGB": 12.1,
    "RAMModuleCount": 2,
    "RAMManufacturer": "Microsoft Corporation",
    "RAMPartNumber": "None",
    "RAMModuleCapacitiesGB": "1 + 15",
    "DiskModel": "Microsoft Virtual Disk",
    "DiskSizeGB": 150.0,
    "DiskMediaType": "Fixed hard disk media",
    "DiskInterfaceType": "SCSI",
    "SystemDriveFreeSpaceGB": 30.9,
    "PowerPlan": "High performance",
    "SystemUptimeHours": 0.6,
    "RunningProcessCount": 128,
    "WindowsDefenderEnabled": true,
    "WindowsDefenderRealTimeProtection": false,
    "PowerShellVersion": "7.6.2",
    "JavaVersion": "21.0.11",
    "JavaDistribution": "\"21.0.11\"",
    "NodeVersion": "v22.22.3",
    "PythonVersion": "Python 3.12.10",
    "GradleVersion": "System.Object[]",
    "KotlinVersion": "Kotlin:        2.2.0"
  },
  {
    "mean": null,
    "median": null,
    "stddev": null,
    "min": null,
    "max": null,
    "ci95_lower": null,
    "ci95_upper": null,
    "executable": "commonmain-k-perf-enabled-true-flushEarly-false-propAccessors-false-testKIR-false-node",
    "buildTimeMs": 5064.5526,
    "RepetitionCount": 3,
    "CleanBuild": false,
    "StepCount": 20,
    "Native": true,
    "Enabled": [
      true
    ],
    "Methods": [
      ".*"
    ],
    "InstrumentPropertyAccessors": [
      false
    ],
    "CILabel": "ci-windows-small",
    "Dedicated": false,
    "JVM": true,
    "JS": true,
    "FlushEarly": [
      false
    ],
    "TestKIR": [
      false
    ],
    "Common": true,
    "Reference": true,
    "CollectionTimestamp": "2026-06-19 04:08:49",
    "GitCommitHash": "be04b4c7ef586e83a5426f6ec6e5baca67cd70f9",
    "GitBranch": "main",
    "DeviceManufacturer": "Microsoft Corporation",
    "DeviceModel": "Virtual Machine",
    "IsVirtualMachine": true,
    "OS": "Microsoft Windows Server 2025 Datacenter 10.0.26100",
    "OSArchitecture": "64-bit",
    "WindowsBuildNumber": "26100",
    "TimeZone": "UTC",
    "Username": "runneradmin",
    "BIOSVersion": "Hyper-V UEFI Release v4.1",
    "BIOSManufacturer": "Microsoft Corporation",
    "SecureBootEnabled": false,
    "HyperVEnabled": true,
    "CPU": "AMD EPYC 9V74 80-Core Processor",
    "CPUCores": 2,
    "CPULogicalProcessors": 4,
    "CPUMaxClockSpeedMHz": 2596,
    "TotalRAMGB": 15.99,
    "AvailableRAMGB": 12.1,
    "RAMModuleCount": 2,
    "RAMManufacturer": "Microsoft Corporation",
    "RAMPartNumber": "None",
    "RAMModuleCapacitiesGB": "1 + 15",
    "DiskModel": "Microsoft Virtual Disk",
    "DiskSizeGB": 150.0,
    "DiskMediaType": "Fixed hard disk media",
    "DiskInterfaceType": "SCSI",
    "SystemDriveFreeSpaceGB": 30.9,
    "PowerPlan": "High performance",
    "SystemUptimeHours": 0.6,
    "RunningProcessCount": 128,
    "WindowsDefenderEnabled": true,
    "WindowsDefenderRealTimeProtection": false,
    "PowerShellVersion": "7.6.2",
    "JavaVersion": "21.0.11",
    "JavaDistribution": "\"21.0.11\"",
    "NodeVersion": "v22.22.3",
    "PythonVersion": "Python 3.12.10",
    "GradleVersion": "System.Object[]",
    "KotlinVersion": "Kotlin:        2.2.0"
  },
  {
    "mean": 77913.0,
    "median": 85222.0,
    "stddev": 6329.819665677688,
    "min": 74236.0,
    "max": 85222.0,
    "ci95_lower": 62198.55072202656,
    "ci95_upper": 93627.44927797344,
    "executable": "commonmain-k-perf-enabled-true-flushEarly-false-propAccessors-false-testKIR-false-win-exe",
    "buildTimeMs": 97657.113,
    "RepetitionCount": 3,
    "CleanBuild": false,
    "StepCount": 20,
    "Native": true,
    "Enabled": [
      true
    ],
    "Methods": [
      ".*"
    ],
    "InstrumentPropertyAccessors": [
      false
    ],
    "CILabel": "ci-windows-small",
    "Dedicated": false,
    "JVM": true,
    "JS": true,
    "FlushEarly": [
      false
    ],
    "TestKIR": [
      false
    ],
    "Common": true,
    "Reference": true,
    "CollectionTimestamp": "2026-06-19 04:08:49",
    "GitCommitHash": "be04b4c7ef586e83a5426f6ec6e5baca67cd70f9",
    "GitBranch": "main",
    "DeviceManufacturer": "Microsoft Corporation",
    "DeviceModel": "Virtual Machine",
    "IsVirtualMachine": true,
    "OS": "Microsoft Windows Server 2025 Datacenter 10.0.26100",
    "OSArchitecture": "64-bit",
    "WindowsBuildNumber": "26100",
    "TimeZone": "UTC",
    "Username": "runneradmin",
    "BIOSVersion": "Hyper-V UEFI Release v4.1",
    "BIOSManufacturer": "Microsoft Corporation",
    "SecureBootEnabled": false,
    "HyperVEnabled": true,
    "CPU": "AMD EPYC 9V74 80-Core Processor",
    "CPUCores": 2,
    "CPULogicalProcessors": 4,
    "CPUMaxClockSpeedMHz": 2596,
    "TotalRAMGB": 15.99,
    "AvailableRAMGB": 12.1,
    "RAMModuleCount": 2,
    "RAMManufacturer": "Microsoft Corporation",
    "RAMPartNumber": "None",
    "RAMModuleCapacitiesGB": "1 + 15",
    "DiskModel": "Microsoft Virtual Disk",
    "DiskSizeGB": 150.0,
    "DiskMediaType": "Fixed hard disk media",
    "DiskInterfaceType": "SCSI",
    "SystemDriveFreeSpaceGB": 30.9,
    "PowerPlan": "High performance",
    "SystemUptimeHours": 0.6,
    "RunningProcessCount": 128,
    "WindowsDefenderEnabled": true,
    "WindowsDefenderRealTimeProtection": false,
    "PowerShellVersion": "7.6.2",
    "JavaVersion": "21.0.11",
    "JavaDistribution": "\"21.0.11\"",
    "NodeVersion": "v22.22.3",
    "PythonVersion": "Python 3.12.10",
    "GradleVersion": "System.Object[]",
    "KotlinVersion": "Kotlin:        2.2.0"
  }
]
